[
  {
    "content_id": 650811,
    "reference_id": 203395,
    "version": "1.0.0",
    "title": "麥基洗德",
    "media_type": "Text",
    "index_reference": "麥基洗德",
    "language": "zht",
    "content": "<p>麥基洗德是聖經中的一位神秘人物。他的名字意為「公義之王」。他是迦南的祭司和王。沒有關於他的家族、出生或死亡的記錄。</p><p>亞伯拉罕在擊敗四位美索不達米亞王後，遇見了麥基洗德。美索不達米亞人襲擊所多瑪和蛾摩拉，並俘虜了亞伯拉罕的侄兒羅得（<a href=\"https://ref.ly/Gen14:1-Gen14:16\">創14:1–16</a>）。當亞伯拉罕從戰鬥中歸來時，撒冷（即耶路撒冷；見<a href=\"https://ref.ly/Ps76:2\">詩76:2</a>及其註腳）王麥基洗德與滿懷感激的死海聯盟諸王在一起。麥基洗德事奉那造天和地的真神，是「至高神的祭司」（<a href=\"https://ref.ly/Gen14:18\">創14:18</a>），給了亞伯拉罕餅、酒和祝福（見<a href=\"https://ref.ly/Ps7:17\">詩7:17</a>，<a href=\"https://ref.ly/Ps47:2\">47:2</a>，<a href=\"https://ref.ly/Ps57:2\">57:2</a>，<a href=\"https://ref.ly/Ps78:56\">78:56</a>）。麥基洗德明白亞伯拉罕敬拜真神，他因著神賜予亞伯拉罕勝利而稱頌神（<a href=\"https://ref.ly/Gen14:19-Gen14:20\">創14:19–20</a>）。亞伯拉罕接受麥基洗德的禮物，並給他十分之一，這顯明麥基洗德的重要性（見<a href=\"https://ref.ly/Heb7:4-Heb7:10\">來7:4–10</a>）。</p><p>創世記記載了許多人的家族歷史，但麥基洗德突然出現，並沒有家譜記錄。他也同樣迅速消失了。在以色列後來的歷史中，大衛王可能想到這一點，他說彌賽亞（神所揀選的那位）是「永遠為祭司，照著麥基洗德的等次」（<a href=\"https://ref.ly/Ps110:4\">詩110:4</a>；參<a href=\"https://ref.ly/Heb7:15-Heb7:25\">來7:15–25</a>）。希伯來書使用麥基洗德沒有家譜的概念，比較了暫時的利未祭司職份，與耶穌基督永恆的祭司職份。希伯來書也解釋說，麥基洗德「<span>與神的兒子相似</span>」，但不是神的兒子（<a href=\"https://ref.ly/Heb7:3\">來7:3</a>）。他的祭司職份永遠持續，預表彌賽亞的祭司職份。耶穌像麥基洗德，但不像以色列的君王，祂是履行祭司職分的君王。</p><p>麥基洗德是有君尊的祭司，比以色列祭司的先祖利未更大。同樣，彌賽亞耶穌基督是比亞倫的後裔更超越的祭司。耶穌獻上了永久赦罪的祭，使人直接進到神面前（<a href=\"https://ref.ly/Heb7:24-Heb7:28\">來7:24–28</a>）。祂是透過聖靈，而不是透過律法引導祂的百姓（<a href=\"https://ref.ly/Heb8:7-Heb8:13\">來8:7–13</a>）。祂是那些信靠祂的人永遠的祭司、君王。</p><p><u>進深研究的經文段落</u></p><p><a href=\"https://ref.ly/Gen14:17-Gen14:24\">創14:17–20</a>；<a href=\"https://ref.ly/Ps110:4\">詩110:4</a>；<a href=\"https://ref.ly/Heb5:6-Heb5:10\">來5:6–10</a>，<a href=\"https://ref.ly/Heb6:20-Heb7:28\">6:20–7:28</a></p>",
    "associations": {
      "passage": [
        {
          "start_ref": "01014018",
          "start_ref_usfm": "GEN 14:18",
          "end_ref": "01014018",
          "end_ref_usfm": "GEN 14:18"
        },
        {
          "start_ref": "19007017",
          "start_ref_usfm": "PSA 7:17",
          "end_ref": "19007017",
          "end_ref_usfm": "PSA 7:17"
        },
        {
          "start_ref": "19047002",
          "start_ref_usfm": "PSA 47:2",
          "end_ref": "19047002",
          "end_ref_usfm": "PSA 47:2"
        },
        {
          "start_ref": "19057002",
          "start_ref_usfm": "PSA 57:2",
          "end_ref": "19057002",
          "end_ref_usfm": "PSA 57:2"
        },
        {
          "start_ref": "19076002",
          "start_ref_usfm": "PSA 76:2",
          "end_ref": "19076002",
          "end_ref_usfm": "PSA 76:2"
        },
        {
          "start_ref": "19078056",
          "start_ref_usfm": "PSA 78:56",
          "end_ref": "19078056",
          "end_ref_usfm": "PSA 78:56"
        },
        {
          "start_ref": "19110004",
          "start_ref_usfm": "PSA 110:4",
          "end_ref": "19110004",
          "end_ref_usfm": "PSA 110:4"
        },
        {
          "start_ref": "58007003",
          "start_ref_usfm": "HEB 7:3",
          "end_ref": "58007003",
          "end_ref_usfm": "HEB 7:3"
        },
        {
          "start_ref": "01014001",
          "start_ref_usfm": "GEN 14:1",
          "end_ref": "01014016",
          "end_ref_usfm": "GEN 14:16"
        },
        {
          "start_ref": "01014017",
          "start_ref_usfm": "GEN 14:17",
          "end_ref": "01014024",
          "end_ref_usfm": "GEN 14:24"
        },
        {
          "start_ref": "58008007",
          "start_ref_usfm": "HEB 8:7",
          "end_ref": "58008013",
          "end_ref_usfm": "HEB 8:13"
        },
        {
          "start_ref": "58007004",
          "start_ref_usfm": "HEB 7:4",
          "end_ref": "58007010",
          "end_ref_usfm": "HEB 7:10"
        },
        {
          "start_ref": "01014019",
          "start_ref_usfm": "GEN 14:19",
          "end_ref": "01014020",
          "end_ref_usfm": "GEN 14:20"
        },
        {
          "start_ref": "58007015",
          "start_ref_usfm": "HEB 7:15",
          "end_ref": "58007025",
          "end_ref_usfm": "HEB 7:25"
        },
        {
          "start_ref": "58007024",
          "start_ref_usfm": "HEB 7:24",
          "end_ref": "58007028",
          "end_ref_usfm": "HEB 7:28"
        },
        {
          "start_ref": "58005006",
          "start_ref_usfm": "HEB 5:6",
          "end_ref": "58005010",
          "end_ref_usfm": "HEB 5:10"
        },
        {
          "start_ref": "58006020",
          "start_ref_usfm": "HEB 6:20",
          "end_ref": "58007028",
          "end_ref_usfm": "HEB 7:28"
        }
      ],
      "resource": []
    }
  }
]